nirtools/__init__.py
nirtools/ir/__init__.py
nirtools/ir/eval.py
nirtools-0.0.2.dist-info/LICENSE
nirtools-0.0.2.dist-info/METADATA
nirtools-0.0.2.dist-info/WHEEL
nirtools-0.0.2.dist-info/top_level.txt
nirtools-0.0.2.dist-info/RECORD
